{"cameraMode":{"drawMode":0,"name":"Shaded","section":"Shading Mode"},"sceneLighting":true,"audioPlay":false,"sceneViewState":{"m_AlwaysRefresh":false,"showFog":true,"showSkybox":true,"showFlares":true,"showImageEffects":true,"showParticleSystems":true,"showVisualEffectGraphs":true,"m_FxEnabled":true},"in2DMode":false,"pivot":{"x":46.715553283691409,"y":10.144423484802246,"z":5.366293430328369},"rotation":{"x":-0.1753673106431961,"y":0.7623205184936523,"z":-0.2310684472322464,"w":-0.5785570740699768},"size":10.0,"orthographic":false}